catboost/__init__.py
catboost/_catboost.so
catboost/carry.py
catboost/core.py
catboost/datasets.py
catboost/dev_utils.py
catboost/metrics.py
catboost/monoforest.py
catboost/plot_helpers.py
catboost/text_processing.py
catboost/utils.py
catboost/version.py
catboost/eval/__init__.py
catboost/eval/_fold_model.py
catboost/eval/_fold_models_handler.py
catboost/eval/_fold_storage.py
catboost/eval/_readers.py
catboost/eval/_splitter.py
catboost/eval/catboost_evaluation.py
catboost/eval/evaluation_result.py
catboost/eval/execution_case.py
catboost/eval/factor_utils.py
catboost/eval/log_config.py
catboost/eval/utils.py
catboost/hnsw/__init__.py
catboost/hnsw/_hnsw.so
catboost/hnsw/hnsw.py
catboost/widget/__init__.py
catboost/widget/callbacks.py
catboost/widget/ipythonwidget.py
catboost/widget/metrics_plotter.py
catboost-1.2.8.data/data/etc/jupyter/nbconfig/notebook.d/catboost-widget.json
catboost-1.2.8.data/data/share/jupyter/labextensions/catboost-widget/package.json
catboost-1.2.8.data/data/share/jupyter/labextensions/catboost-widget/static/138.c8bd59d1ac66cac18152.js
catboost-1.2.8.data/data/share/jupyter/labextensions/catboost-widget/static/479.d43617224b25ecf15b1d.js
catboost-1.2.8.data/data/share/jupyter/labextensions/catboost-widget/static/479.d43617224b25ecf15b1d.js.LICENSE.txt
catboost-1.2.8.data/data/share/jupyter/labextensions/catboost-widget/static/486.bafd26b008c3405f7750.js
catboost-1.2.8.data/data/share/jupyter/labextensions/catboost-widget/static/486.bafd26b008c3405f7750.js.LICENSE.txt
catboost-1.2.8.data/data/share/jupyter/labextensions/catboost-widget/static/755.297bcad6e07632169fc2.js
catboost-1.2.8.data/data/share/jupyter/labextensions/catboost-widget/static/755.297bcad6e07632169fc2.js.LICENSE.txt
catboost-1.2.8.data/data/share/jupyter/labextensions/catboost-widget/static/908.81f6af6c7d6425b98663.js
catboost-1.2.8.data/data/share/jupyter/labextensions/catboost-widget/static/remoteEntry.bb0af8065c14acd4d841.js
catboost-1.2.8.dist-info/METADATA
catboost-1.2.8.dist-info/WHEEL
catboost-1.2.8.dist-info/top_level.txt
catboost-1.2.8.dist-info/RECORD
